{
    "authorize" : {
        ".*" : "",
        "schema.*": "r",
        "token": "cr",
        "token.accountId": "r",
        "token.accountId": "r",
        "token.clientId": "r",
        "token.code": "cr",
        "token.defaultProject": "r",
        "token.enabled": "r",
        "token.hostname": "r",
        "token.identities": "r",
        "token.jwt": "r",
        "token.orgs": "r",
        "token.security": "r",
        "token.teams": "r",
        "token.user": "r",
        "token.userIdentity": "r",
        "token.authProvider": "r",
        "token.userType": "r"
    }
}
